tabularasa/__init__.py
tabularasa/conftest.py
tabularasa/examples/examples.py
tabularasa/source/some_module.py
tabularasa/test/shorthand.py
tabularasa/test/test_something.py
tabularasa-0.1.104.dist-info/LICENSE.txt
tabularasa-0.1.104.dist-info/METADATA
tabularasa-0.1.104.dist-info/WHEEL
tabularasa-0.1.104.dist-info/top_level.txt
tabularasa-0.1.104.dist-info/RECORD
